fetch_cache/__init__.py
fetch_cache/cache/__init__.py
fetch_cache/cache/base.py
fetch_cache/cache/django_cache.py
fetch_cache/cache/file.py
fetch_cache/cache/memory.py
fetch_cache/cache/mongo_cache.py
fetch_cache/cache/redis_cache.py
fetch_cache/cache/sql_cache.py
fetch_cache/core.py
fetch_cache/utils/__init__.py
fetch_cache/utils/async_sync.py
fetch_cache/utils/timing.py
fetch_cache-0.1.3.dist-info/METADATA
fetch_cache-0.1.3.dist-info/WHEEL
fetch_cache-0.1.3.dist-info/RECORD
