Metadata-Version: 2.1
Name: fetch_cache
Version: 0.1.3
Summary: An HTTP client with multiple cache backends to optimize repeated request performance
Home-page: https://github.com/xiwen-haochi/fetch_cache
License: MIT
Keywords: http,cache,httpx,db,sql,redis,mongo,django
Author: 'fkl'
Author-email: 18654198191@163.com
Requires-Python: >=3.8
Classifier: Development Status :: 4 - Beta
Classifier: Intended Audience :: Developers
Classifier: License :: OSI Approved :: MIT License
Classifier: Programming Language :: Python :: 3
Classifier: Programming Language :: Python :: 3.8
Classifier: Programming Language :: Python :: 3.9
Classifier: Programming Language :: Python :: 3.10
Classifier: Programming Language :: Python :: 3.11
Classifier: Programming Language :: Python :: 3.12
Classifier: Programming Language :: Python :: 3.13
Classifier: Programming Language :: Python :: 3.6
Classifier: Programming Language :: Python :: 3.7
Requires-Dist: httpx (>=0.22.0)
Project-URL: Repository, https://github.com/xiwen-haochi/fetch_cache
